blox1module/__init__.py
blox1module/b1_dns_record.py
blox1module-0.0.3.dist-info/METADATA
blox1module-0.0.3.dist-info/WHEEL
blox1module-0.0.3.dist-info/top_level.txt
blox1module-0.0.3.dist-info/RECORD
